{
  "configVersion": 1,
  "timestamp": 1637268146206,
  "index": "/index.html",
  "assetGroups": [
    {
      "name": "app",
      "installMode": "prefetch",
      "updateMode": "prefetch",
      "cacheQueryOptions": {
        "ignoreVary": true
      },
      "urls": [
        "/664.4c5bc31a62cfbbde7065.js",
        "/favicon.ico",
        "/index.html",
        "/main.86c9495a0e66d109b32d.js",
        "/manifest.webmanifest",
        "/polyfills.e8ca9b4573a1f1bf1813.js",
        "/runtime.e7c97ed000417abacff9.js",
        "/styles.f5898e03354af6e468ad.css"
      ],
      "patterns": []
    },
    {
      "name": "assets",
      "installMode": "lazy",
      "updateMode": "prefetch",
      "cacheQueryOptions": {
        "ignoreVary": true
      },
      "urls": [
        "/assets/icons/icon-128x128.png",
        "/assets/icons/icon-144x144.png",
        "/assets/icons/icon-152x152.png",
        "/assets/icons/icon-192x192.png",
        "/assets/icons/icon-384x384.png",
        "/assets/icons/icon-512x512.png",
        "/assets/icons/icon-72x72.png",
        "/assets/icons/icon-96x96.png",
        "/assets/images/E1.png",
        "/assets/images/E2.png",
        "/assets/images/E3.png",
        "/assets/images/ED1.png",
        "/assets/images/bloc examen.png",
        "/assets/images/bronce.png",
        "/assets/images/cerpentinas de la recompenza.png",
        "/assets/images/cofre rfecompenza.png",
        "/assets/images/comunicacion.png",
        "/assets/images/corona amarilla.png",
        "/assets/images/corona gris.png",
        "/assets/images/doctor inostrosa.png",
        "/assets/images/etiqueta de pagina facil.png",
        "/assets/images/hombre con pesas.png",
        "/assets/images/imagen 1 corriente.png",
        "/assets/images/imagen 1.1 corriente.png",
        "/assets/images/imagen 1.2 corriente.png",
        "/assets/images/logeo.jpg",
        "/assets/images/logo-form.png",
        "/assets/images/logo.png",
        "/assets/images/mg. duglas.png",
        "/assets/images/mg. olga.png",
        "/assets/images/monedas con brillo recompenza.png",
        "/assets/images/oro.png",
        "/assets/images/personajes anuncios.png",
        "/assets/images/plata.png",
        "/assets/images/quijote01.png",
        "/assets/images/razonamiento_verbal.png",
        "/assets/images/usuario.png",
        "/assets/js/razonamiento.js"
      ],
      "patterns": []
    }
  ],
  "dataGroups": [
    {
      "name": "school-api",
      "patterns": [
        "https:\\/\\/api\\.yachachiykunallapanchispaq\\.com\\/api\\/[^/]*"
      ],
      "strategy": "performance",
      "maxSize": 10000,
      "maxAge": 36000000,
      "timeoutMs": 5000,
      "cacheQueryOptions": {
        "ignoreVary": true
      },
      "version": 1
    }
  ],
  "hashTable": {
    "/664.4c5bc31a62cfbbde7065.js": "16cf12667662a0888383a6fe7f2fea187cad58f5",
    "/assets/icons/icon-128x128.png": "dae3b6ed49bdaf4327b92531d4b5b4a5d30c7532",
    "/assets/icons/icon-144x144.png": "b0bd89982e08f9bd2b642928f5391915b74799a7",
    "/assets/icons/icon-152x152.png": "7479a9477815dfd9668d60f8b3b2fba709b91310",
    "/assets/icons/icon-192x192.png": "1abd80d431a237a853ce38147d8c63752f10933b",
    "/assets/icons/icon-384x384.png": "329749cd6393768d3131ed6304c136b1ca05f2fd",
    "/assets/icons/icon-512x512.png": "559d9c4318b45a1f2b10596bbb4c960fe521dbcc",
    "/assets/icons/icon-72x72.png": "c457e56089a36952cd67156f9996bc4ce54a5ed9",
    "/assets/icons/icon-96x96.png": "3914125a4b445bf111c5627875fc190f560daa41",
    "/assets/images/E1.png": "f71ad4a86469e8aacea9ca79a19a760cd03b261b",
    "/assets/images/E2.png": "941642da1f8906e415adac29f22fbb704913f3ec",
    "/assets/images/E3.png": "78735852a35bc8a4c0317d38f4985f0d5d6bbea7",
    "/assets/images/ED1.png": "f75ebf9c8397eafec3d58d29b41fc6881d9926e4",
    "/assets/images/bloc examen.png": "540e91d38b01fd21b37aedb81b780234737ee2f4",
    "/assets/images/bronce.png": "31be41a6bf578d45ce5398f84c0a6ac1d8a7145c",
    "/assets/images/cerpentinas de la recompenza.png": "b56037cf45365690e540313e85f7cd17a8b114b4",
    "/assets/images/cofre rfecompenza.png": "8a3b2a8a4370e3602cf84acae8736e30684f43fb",
    "/assets/images/comunicacion.png": "e8e6135ee20eeb7064cc328d43644efcd78d4fd8",
    "/assets/images/corona amarilla.png": "3b7823daaad1cb3134336ee89f532fc2bd63c879",
    "/assets/images/corona gris.png": "2d3cfd1a8b430ae26a5d5c8e6df2fa49b4dcf0fb",
    "/assets/images/doctor inostrosa.png": "d99e352186da535252fc6e6b9537016d0be7dd2e",
    "/assets/images/etiqueta de pagina facil.png": "9ab9ec8282e4343a4b84d6ed43604323743c5748",
    "/assets/images/hombre con pesas.png": "14bb5796789dc339786a661d79f54a616fe106c3",
    "/assets/images/imagen 1 corriente.png": "ac8705132c5ea7ab03cb3755472b3b9d5a72a10d",
    "/assets/images/imagen 1.1 corriente.png": "fae0a55839ebe7ce0f094b9dd4f4ef579ebfe7ae",
    "/assets/images/imagen 1.2 corriente.png": "c44129646408d66447bdfb9a1c569f6debd4b94e",
    "/assets/images/logeo.jpg": "fc55df00c42a20affd7f8790701cd82aa3407483",
    "/assets/images/logo-form.png": "c329ea74dc94198dc9f9fb2fc53eb35a562235ea",
    "/assets/images/logo.png": "ea1b462384a67644af186b6bf704473aaee0a699",
    "/assets/images/mg. duglas.png": "59386dcc2b98c413f4132b06e67742d50c8f7ce8",
    "/assets/images/mg. olga.png": "dbd06fdff13fa1cb0555ff30fc4fdfa54adf026d",
    "/assets/images/monedas con brillo recompenza.png": "940023148035dc62d655d0eb80d43e8af2c5821b",
    "/assets/images/oro.png": "23169ad6607a758211d24dbecdd538c315faf58a",
    "/assets/images/personajes anuncios.png": "2095a5cd4587084f3780035d8403de413000325d",
    "/assets/images/plata.png": "d84038ad2f7c671168fc3ced7b0309705cff915e",
    "/assets/images/quijote01.png": "4bb607db0ee47a03ab12754d8315fb636e8605b7",
    "/assets/images/razonamiento_verbal.png": "a0b06181ebfac28769631f4f0606af71053cc24e",
    "/assets/images/usuario.png": "7c40c1a4c99e39a54ea0c6aeb43d015c97b1219c",
    "/assets/js/razonamiento.js": "3db6e2cd0958443de9c702bcbc143233ba182737",
    "/favicon.ico": "22f6a4a3bcaafafb0254e0f2fa4ceb89e505e8b2",
    "/index.html": "8b9cbcb74a6d29587320a5e81cee7d683bd8429f",
    "/main.86c9495a0e66d109b32d.js": "a70a2df29acd49747b130a2a9cd671e46b59dfdf",
    "/manifest.webmanifest": "0525a045ed472918dea972e744b31758ac30393b",
    "/polyfills.e8ca9b4573a1f1bf1813.js": "50a9cd3a952259c5b29451c1e48d1028bcd5f760",
    "/runtime.e7c97ed000417abacff9.js": "be706cdb35ae20cbd96bd85cc5e89ba1965a0ae0",
    "/styles.f5898e03354af6e468ad.css": "e1f80d6605e2392fe990e2adc3975f5637af0909"
  },
  "navigationUrls": [
    {
      "positive": true,
      "regex": "^\\/.*$"
    },
    {
      "positive": false,
      "regex": "^\\/(?:.+\\/)?[^/]*\\.[^/]*$"
    },
    {
      "positive": false,
      "regex": "^\\/(?:.+\\/)?[^/]*__[^/]*$"
    },
    {
      "positive": false,
      "regex": "^\\/(?:.+\\/)?[^/]*__[^/]*\\/.*$"
    }
  ],
  "navigationRequestStrategy": "performance"
}